sidoware/__init__.py
sidoware/core/__init__.py
sidoware/lify/__init__.py
sidoware/lify/commandmanager.py
sidoware/lify/os/__init__.py
sidoware/lify/project/__init__.py
sidoware/lify/project/projectmanager.py
sidoware/lify/project/data/__init__.py
sidoware/lify/project/data/configurationdata.py
sidoware/lify/project/data/packagedata.py
sidoware/lify/project/data/projectdata.py
lify-0.0.8.dist-info/LICENSE
lify-0.0.8.dist-info/METADATA
lify-0.0.8.dist-info/WHEEL
lify-0.0.8.dist-info/entry_points.txt
lify-0.0.8.dist-info/top_level.txt
lify-0.0.8.dist-info/RECORD
